spark_webdat_tools/__init__.py
spark_webdat_tools/functions/__init__.py
spark_webdat_tools/functions/jira.py
spark_webdat_tools/functions/runserver.py
spark_webdat_tools/src/__init__.py
spark_webdat_tools/src/main.py
spark_webdat_tools/src/runserver.py
spark_webdat_tools-0.3.9.dist-info/LICENSE
spark_webdat_tools-0.3.9.dist-info/METADATA
spark_webdat_tools-0.3.9.dist-info/WHEEL
spark_webdat_tools-0.3.9.dist-info/top_level.txt
spark_webdat_tools-0.3.9.dist-info/RECORD
