Metadata-Version: 2.1
Name: spark-webdat-tools
Version: 0.3.9
Summary: spark_webdat_tools
Home-page: https://github.com/jonaqp/spark_webdat_tools/
Download-URL: https://github.com/jonaqp/spark_webdat_tools/archive/main.zip
Author: Jonathan Quiza
Author-email: jony327@gmail.com
Keywords: spark,repository,dataproc
Classifier: Development Status :: 5 - Production/Stable
Classifier: Intended Audience :: Developers
Classifier: Intended Audience :: Science/Research
Classifier: Topic :: Scientific/Engineering :: Artificial Intelligence
Classifier: License :: OSI Approved :: Apache Software License
Classifier: Programming Language :: Python :: 3.9
License-File: LICENSE
Requires-Dist: spark-dataframe-tools
Requires-Dist: prettytable ==3.9.0
Requires-Dist: openpyxl ==3.1.2
